LICENSE
MANIFEST.in
README.rst
setup.py
src/vconnector-cli
src/vconnector/__init__.py
src/vconnector/cache.py
src/vconnector/core.py
src/vconnector/exceptions.py
src/vconnector.egg-info/PKG-INFO
src/vconnector.egg-info/SOURCES.txt
src/vconnector.egg-info/dependency_links.txt
src/vconnector.egg-info/requires.txt
src/vconnector.egg-info/top_level.txt