Metadata-Version: 1.1
Name: vconnector
Version: 0.5.3
Summary: VMware vSphere Connector Module for Python
Home-page: https://github.com/dnaeon/py-vconnector
Author: Marin Atanasov Nikolov
Author-email: dnaeon@gmail.com
License: BSD
Download-URL: https://github.com/dnaeon/py-vconnector/releases
Platform: UNKNOWN
